odoo/addons/web_company_title/README.rst
odoo/addons/web_company_title/__init__.py
odoo/addons/web_company_title/__manifest__.py
odoo/addons/web_company_title/i18n/web_company_title.pot
odoo/addons/web_company_title/readme/DESCRIPTION.rst
odoo/addons/web_company_title/static/description/icon.png
odoo/addons/web_company_title/static/description/index.html
odoo/addons/web_company_title/static/src/js/web_company_title.js
odoo/addons/web_company_title/views/assets.xml
odoo11_addon_web_company_title-11.0.1.0.2.dist-info/METADATA
odoo11_addon_web_company_title-11.0.1.0.2.dist-info/WHEEL
odoo11_addon_web_company_title-11.0.1.0.2.dist-info/top_level.txt
odoo11_addon_web_company_title-11.0.1.0.2.dist-info/RECORD
